tok715/constants.py
tok715/vectorstor/cli.py
tok715/vendor/nls/__init__.py
tok715/vendor/nls/core.py
tok715/vendor/nls/exception.py
tok715/vendor/nls/logging.py
tok715/vendor/nls/speech_recognizer.py
tok715/vendor/nls/speech_synthesizer.py
tok715/vendor/nls/speech_transcriber.py
tok715/vendor/nls/token.py
tok715/vendor/nls/util.py
tok715/vendor/nls/version.py
tok715/vendor/nls/websocket/__init__.py
tok715/vendor/nls/websocket/_abnf.py
tok715/vendor/nls/websocket/_app.py
tok715/vendor/nls/websocket/_cookiejar.py
tok715/vendor/nls/websocket/_core.py
tok715/vendor/nls/websocket/_exceptions.py
tok715/vendor/nls/websocket/_handshake.py
tok715/vendor/nls/websocket/_http.py
tok715/vendor/nls/websocket/_logging.py
tok715/vendor/nls/websocket/_socket.py
tok715/vendor/nls/websocket/_ssl_compat.py
tok715/vendor/nls/websocket/_url.py
tok715/vendor/nls/websocket/_utils.py
tok715/vendor/nls/websocket/tests/__init__.py
tok715/vendor/nls/websocket/tests/data/header01.txt
tok715/vendor/nls/websocket/tests/data/header02.txt
tok715/vendor/nls/websocket/tests/data/header03.txt
tok715/vendor/nls/websocket/tests/echo-server.py
tok715/vendor/nls/websocket/tests/test_abnf.py
tok715/vendor/nls/websocket/tests/test_app.py
tok715/vendor/nls/websocket/tests/test_cookiejar.py
tok715/vendor/nls/websocket/tests/test_http.py
tok715/vendor/nls/websocket/tests/test_url.py
tok715/vendor/nls/websocket/tests/test_websocket.py
tok715/voicerecog/cli.py
tok715-0.0.2.dist-info/LICENSE
tok715-0.0.2.dist-info/METADATA
tok715-0.0.2.dist-info/WHEEL
tok715-0.0.2.dist-info/entry_points.txt
tok715-0.0.2.dist-info/RECORD
