Metadata-Version: 2.1
Name: tok715
Version: 0.0.2
Summary: CODENAME: TOK715
License: MIT
Author: GUO YANKE
Author-email: hi@guoyk.xyz
Requires-Python: >=3.10,<4.0
Classifier: License :: OSI Approved :: MIT License
Classifier: Programming Language :: Python :: 3
Classifier: Programming Language :: Python :: 3.10
Classifier: Programming Language :: Python :: 3.11
Requires-Dist: PyMySQL (>=1.1,<2.0)
Requires-Dist: PyYAML (>=6.0,<7.0)
Requires-Dist: SQLAlchemy (>=2.0,<3.0)
Requires-Dist: aliyun-python-sdk-core (>=2.13.3)
Requires-Dist: click (>=8.1,<9.0)
Requires-Dist: matplotlib (>=3.3.4)
Requires-Dist: oss2 (>=2.18.2,<3.0.0)
Requires-Dist: pika (>=1.3,<2.0)
Requires-Dist: pymilvus (>=2.3,<3.0)
Requires-Dist: redis[hiredis] (>=5.0.1,<6.0.0)
Requires-Dist: torch (>=2.1,<3.0)
Requires-Dist: torchaudio (>=2.1,<3.0)
Requires-Dist: torchvision (>=0.16,<0.17)
Requires-Dist: transformers (>=4.34,<5.0)
